{
  "manifestVersion" : 2,
  "targets" : {
    "TestApplication" : [
      "bazel-bin\/TestSuite\/TestApplication.ipa"
    ],
    "TestSuiteXCTest" : [
      "bazel-bin\/TestSuite\/TestApplication.ipa",
      "bazel-bin\/TestSuite\/TestSuiteXCTest.ipa"
    ],
    "tagged_xctest_2" : [
      "bazel-bin\/TestSuite\/TestApplication.ipa",
      "bazel-bin\/TestSuite\/Three\/tagged_xctest_2.ipa"
    ],
    "_bazel_clean_" : [

    ],
    "_idx_tagged_xctest_1_Binary_TestSuiteXCTest_tagged_xctest_2_97DFB03E" : [

    ],
    "tagged_xctest_1" : [
      "bazel-bin\/TestSuite\/TestApplication.ipa",
      "bazel-bin\/TestSuite\/Three\/tagged_xctest_1.ipa"
    ]
  },
  "artifacts" : [
    "TestApplication.app\/**",
    "TestSuiteXCTest.xctest\/**",
    "bazel-bin\/TestSuite\/TestApplication-MergedInfo.plist",
    "lib_idx_tagged_xctest_1_Binary_TestSuiteXCTest_tagged_xctest_2_97DFB03E.a",
    "tagged_xctest_1.xctest\/**",
    "tagged_xctest_2.xctest\/**"
  ],
  "fileReferences" : [
    "..\/..\/TestSuite\/BUILD",
    "..\/..\/TestSuite\/Binary\/srcs\/main.m",
    "..\/..\/TestSuite\/TestSuite\/TestSuiteXCTest.m",
    "..\/..\/TestSuite\/Three\/BUILD",
    "..\/..\/TestSuite\/Three\/tagged_xctest_1.m",
    "..\/..\/TestSuite\/Three\/tagged_xctest_2.m"
  ]
}
